setup.cfg
setup.py
pandasjsonfield/__init__.py
pandasjsonfield/fields.py
pandasjsonfield/models.py
pandasjsonfield/tests.py
pandasjsonfield.egg-info/PKG-INFO
pandasjsonfield.egg-info/SOURCES.txt
pandasjsonfield.egg-info/dependency_links.txt
pandasjsonfield.egg-info/top_level.txt