Metadata-Version: 1.1
Name: pandasjsonfield
Version: 1.0
Summary: Django model field for pandas objects (Series and DataFrame)
Home-page: https://github.com/stellasia/django-pandasjsonfield
Author: Estelle Scifo
Author-email: stell4sia@gmail.com
License: UNKNOWN
Download-URL: https://github.com/stellasia/django-pandasjsonfield/archive/1.0.tar.gz
Keywords: django,model field,pandas
Platform: UNKNOWN
